tests/migrations/0001_initial.py
tests/migrations/0002_advert_sponsoredpage.py
tests/migrations/0003_sectionedpage_sectionedpagesection.py
tests/migrations/0004_pagewithrichtext.py
tests/migrations/0005_pagewithstreamfield.py
tests/migrations/0006_pagewithparentalmanytomany.py
tests/migrations/0007_modelwithmanytomany.py
tests/migrations/0008_author.py
tests/migrations/0009_categories.py
tests/migrations/0010_avatar.py
tests/migrations/0011_redirectpage.py
tests/migrations/0012_pagewithrelatedpages.py
tests/migrations/0013_pagechooserblock_nonrequired.py
tests/migrations/0014_rich_text_nullable.py
tests/migrations/0015_longadvert.py
tests/migrations/0016_advert_tags.py
tests/migrations/0017_correctmodeltypes.py
tests/migrations/0018_alter_pagewithrelatedpages_related_pages_and_more.py
tests/migrations/__init__.py
tests/tests/__init__.py
tests/tests/test_api.py
tests/tests/test_import.py
tests/tests/test_views.py
wagtail_transfer/__init__.py
wagtail_transfer/admin_urls.py
wagtail_transfer/apps.py
wagtail_transfer/auth.py
wagtail_transfer/field_adapters.py
wagtail_transfer/files.py
wagtail_transfer/locators.py
wagtail_transfer/models.py
wagtail_transfer/operations.py
wagtail_transfer/richtext.py
wagtail_transfer/serializers.py
wagtail_transfer/streamfield.py
wagtail_transfer/urls.py
wagtail_transfer/views.py
wagtail_transfer/wagtail_hooks.py
wagtail_transfer/management/__init__.py
wagtail_transfer/management/commands/__init__.py
wagtail_transfer/management/commands/preseed_transfer_table.py
wagtail_transfer/migrations/0001_initial.py
wagtail_transfer/migrations/0002_importedfile.py
wagtail_transfer/migrations/0003_permissions.py
wagtail_transfer/migrations/__init__.py
wagtail_transfer/static/wagtail_transfer/css/transfer-styles.css
wagtail_transfer/static/wagtail_transfer/js/wagtail_transfer.js
wagtail_transfer/static_src/index.js
wagtail_transfer/static_src/chooser/ModelChooser.js
wagtail_transfer/static_src/chooser/ModelChooserPagination.js
wagtail_transfer-0.10.dist-info/licenses/LICENSE
wagtail_transfer-0.10.dist-info/METADATA
wagtail_transfer-0.10.dist-info/WHEEL
wagtail_transfer-0.10.dist-info/top_level.txt
wagtail_transfer-0.10.dist-info/RECORD
