Metadata-Version: 2.4
Name: wagtail-transfer
Version: 0.10
Summary: Content transfer for Wagtail
Home-page: https://github.com/wagtail/wagtail-transfer
Author: Matthew Westcott
Author-email: matthew.westcott@torchbox.com
License: BSD
Classifier: Development Status :: 4 - Beta
Classifier: Environment :: Web Environment
Classifier: Intended Audience :: Developers
Classifier: License :: OSI Approved :: BSD License
Classifier: Operating System :: OS Independent
Classifier: Programming Language :: Python
Classifier: Programming Language :: Python :: 3
Classifier: Programming Language :: Python :: 3.9
Classifier: Programming Language :: Python :: 3.10
Classifier: Programming Language :: Python :: 3.11
Classifier: Programming Language :: Python :: 3.12
Classifier: Programming Language :: Python :: 3.13
Classifier: Framework :: Django
Classifier: Framework :: Django :: 4.2
Classifier: Framework :: Django :: 5.1
Classifier: Framework :: Django :: 5.2
Classifier: Framework :: Wagtail
Classifier: Framework :: Wagtail :: 6
Classifier: Framework :: Wagtail :: 7
Requires-Python: >=3.9
License-File: LICENSE
Requires-Dist: wagtail>=5.2
Provides-Extra: docs
Requires-Dist: mkdocs<1.1,>=1.0; extra == "docs"
Requires-Dist: mkdocs-material<4.7,>=4.6; extra == "docs"
Dynamic: author
Dynamic: author-email
Dynamic: classifier
Dynamic: description
Dynamic: home-page
Dynamic: license
Dynamic: license-file
Dynamic: provides-extra
Dynamic: requires-dist
Dynamic: requires-python
Dynamic: summary
